mappings/__init__.py
mappings/qtcore.py
mappings/qtgui.py
mappings/qtwidgets.py
pysideup-1.0.1.dist-info/METADATA
pysideup-1.0.1.dist-info/WHEEL
pysideup-1.0.1.dist-info/entry_points.txt
pysideup-1.0.1.dist-info/top_level.txt
pysideup-1.0.1.dist-info/RECORD
