Metadata-Version: 2.1
Name: pysideup
Version: 1.0.1
Summary: A tool for converting PySide2 code to PySide6
Home-page: https://github.com/DongHoonPark/pysideup
Author: DongHoon Park
Author-email: donghun94@gmail.com
License: UNKNOWN
Platform: UNKNOWN
Classifier: Programming Language :: Python :: 3
Classifier: License :: OSI Approved :: MIT License
Classifier: Operating System :: OS Independent
Requires-Python: >=3.6
Requires-Dist: astor
